upvest/__init__.py
upvest/__pkginfo__.py
upvest/authentication.py
upvest/clientele.py
upvest/config.py
upvest/exceptions.py
upvest/historical.py
upvest/model.py
upvest/tenancy.py
upvest/utils.py
upvest/proto/__init__.py
upvest/proto/recoverykit_pb2.py
upvest-0.0.10.dist-info/LICENSE
upvest-0.0.10.dist-info/METADATA
upvest-0.0.10.dist-info/WHEEL
upvest-0.0.10.dist-info/top_level.txt
upvest-0.0.10.dist-info/RECORD
