Metadata-Version: 2.1
Name: upvest
Version: 0.0.10
Summary: Upvest API client library
Home-page: https://github.com/upvestco/upvest-python/
Author: Upvest GmbH
Author-email: tech@upvest.co
Maintainer: Alexander Reichhardt
Maintainer-email: alexander@upvest.co
License: MIT
Keywords: api,upvest,bitcoin,ethereum,oauth2,client
Platform: UNKNOWN
Classifier: Development Status :: 4 - Beta
Classifier: Intended Audience :: Developers
Classifier: License :: OSI Approved :: MIT License
Classifier: Operating System :: OS Independent
Classifier: Programming Language :: Python :: 3.7
Classifier: Programming Language :: Python :: 3.8
Classifier: Topic :: Software Development :: Libraries :: Python Modules
Requires-Dist: requests (<3,>=2.21.0)
Requires-Dist: environs (==4.1.0)
Provides-Extra: dev
Requires-Dist: pre-commit (==1.10.5) ; extra == 'dev'
Requires-Dist: prospector (==1.1.6.2) ; extra == 'dev'
Provides-Extra: recovery
Requires-Dist: protobuf (>=3.9.1) ; extra == 'recovery'
Requires-Dist: PyNaCl (>=1.3.0) ; extra == 'recovery'
Provides-Extra: test
Requires-Dist: pytest (==5.2.1) ; extra == 'test'
Requires-Dist: py-ecc (==1.7.0) ; extra == 'test'
Requires-Dist: pysha3 (==1.0.2) ; extra == 'test'
Requires-Dist: bitcoin (==1.1.42) ; extra == 'test'
Requires-Dist: web3 (==5.5.0) ; extra == 'test'
